labtasker_plugin_task_count/__init__.py
labtasker_plugin_task_count/impl.py
labtasker_plugin_task_count/main.py
labtasker_plugin_task_count-0.1.1.dist-info/METADATA
labtasker_plugin_task_count-0.1.1.dist-info/WHEEL
labtasker_plugin_task_count-0.1.1.dist-info/entry_points.txt
labtasker_plugin_task_count-0.1.1.dist-info/top_level.txt
labtasker_plugin_task_count-0.1.1.dist-info/RECORD
