Metadata-Version: 2.4
Name: labtasker-plugin-task-count
Version: 0.1.1
Summary: A demo CLI plugin for Labtasker.
Author-email: Your Name <your.email@example.com>
License: MIT
Classifier: Intended Audience :: Science/Research
Classifier: License :: OSI Approved :: MIT License
Classifier: Operating System :: OS Independent
Classifier: Programming Language :: Python :: 3
Classifier: Programming Language :: Python :: 3.8
Classifier: Programming Language :: Python :: 3.9
Classifier: Programming Language :: Python :: 3.10
Classifier: Programming Language :: Python :: 3.11
Classifier: Programming Language :: Python :: 3.12
Classifier: Programming Language :: Python :: 3.13
Requires-Python: <4.0,>=3.8.1
Requires-Dist: labtasker
